{
  "_producer": "neuralretail-lineage/2.0",
  "_schemaURL": "https://openlineage.io/spec/2-0-2/OpenLineage.json",
  "eventType": "COMPLETE",
  "eventTime": "2026-05-20T14:37:08.905874+00:00",
  "run": {
    "runId": "1c36d708-82b1-489b-b043-2927c92852a3",
    "facets": {
      "batch_size": 50,
      "valid_records": 47,
      "dlq_records": 3
    }
  },
  "job": {
    "namespace": "neuralretail",
    "name": "kafka_ingestion_mock",
    "facets": {
      "processing_engine": {
        "_producer": "neuralretail-lineage/2.0",
        "_schemaURL": "https://openlineage.io/spec/facets/1-2-2/ProcessingEngineRunFacet.json",
        "version": "3.11",
        "name": "python"
      }
    }
  },
  "inputs": [
    {
      "namespace": "mock",
      "name": "mock://pos_transactions",
      "facets": {}
    }
  ],
  "outputs": [
    {
      "namespace": "neuralretail",
      "name": "bronze/transactions.parquet",
      "facets": {}
    }
  ]
}